Metadata-Version: 2.1
Name: blogutils
Version: 0.0.2
Summary: A package for blog-related utilities
Author: Arvind Srivastav
Author-email: alwen1928@gmail.com
Classifier: Programming Language :: Python :: 3
Classifier: License :: OSI Approved :: MIT License
Classifier: Operating System :: OS Independent
Requires-Python: >=3.6
License-File: LICENCE.txt
